omu_eddy_covariance/__init__.py
omu_eddy_covariance/commons/hotspot_data.py
omu_eddy_covariance/commons/monthly_converter.py
omu_eddy_covariance/footprint/flux_footprint_analyzer.py
omu_eddy_covariance/mobile/mobile_spatial_analyzer.py
omu_eddy_covariance/transfer_function/fft_file_reorganizer.py
omu_eddy_covariance/transfer_function/transfer_function_calculator.py
omu_eddy_covariance/ultra/eddydata_preprocessor.py
omu_eddy_covariance/ultra/spectrum_calculator.py
omu_eddy_covariance/ultra/ultra_monthly_analyzer.py
omu_eddy_covariance-0.4.0.dist-info/METADATA
omu_eddy_covariance-0.4.0.dist-info/WHEEL
omu_eddy_covariance-0.4.0.dist-info/licenses/LICENSE
omu_eddy_covariance-0.4.0.dist-info/RECORD
