Metadata-Version: 2.3
Name: omu-eddy-covariance
Version: 0.4.0
Summary: This package provides methods for analyzing atmospheric observation data, primarily eddy covariance methods.
Project-URL: Homepage, https://github.com/omu-meteorology/omu-eddy-covariance
Project-URL: Bug Tracker, https://github.com/omu-meteorology/omu-eddy-covariance/issues
Author-email: connect0459 <connect0459@gmail.com>
License: MIT
Keywords: cospectrum,covariance,eddy,flux,meteorology,omu,powerspectrum,spectrum
Classifier: Development Status :: 3 - Alpha
Classifier: Intended Audience :: Science/Research
Classifier: License :: OSI Approved :: MIT License
Classifier: Programming Language :: Python :: 3
Classifier: Programming Language :: Python :: 3.11
Classifier: Topic :: Scientific/Engineering :: Atmospheric Science
Requires-Python: >=3.11
Requires-Dist: contextily>=1.6.2
Requires-Dist: folium>=0.18.0
Requires-Dist: geopandas>=1.0.1
Requires-Dist: jpholiday
Requires-Dist: matplotlib
Requires-Dist: numpy
Requires-Dist: openpyxl>=3.1.5
Requires-Dist: pandas
Requires-Dist: pillow
Requires-Dist: pyproj>=3.7.0
Requires-Dist: scipy
Requires-Dist: shapely>=2.0.6
Requires-Dist: tqdm
